src/httpcode/__main__.py
src/httpcode/codes.json
hhttpcode-1.0.5.dist-info/METADATA
hhttpcode-1.0.5.dist-info/WHEEL
hhttpcode-1.0.5.dist-info/entry_points.txt
hhttpcode-1.0.5.dist-info/licenses/LICENSE
hhttpcode-1.0.5.dist-info/RECORD
