Metadata-Version: 2.4
Name: hhttpcode
Version: 1.0.5
Summary: Quickly look up HTTP codes in the terminal
Project-URL: Homepage, https://github.com/hamolicious/HTTP-Code-Lookup
Project-URL: Issues, https://github.com/hamolicious/HTTP-Code-Lookup/issues
Author-email: hamolicious <hamolicious@hamolicious.net>
License-File: LICENSE
Classifier: License :: OSI Approved :: MIT License
Classifier: Operating System :: OS Independent
Classifier: Programming Language :: Python :: 3
Requires-Python: >=3.10
Requires-Dist: colorama==0.4.6
Requires-Dist: fire==0.5.0
Requires-Dist: six==1.16.0
Requires-Dist: termcolor==2.4.0
